lfkbenchmark.cpython-310-aarch64-linux-gnu.so
lfkbenchmark-1.0.0b4.dist-info/LICENSE
lfkbenchmark-1.0.0b4.dist-info/METADATA
lfkbenchmark-1.0.0b4.dist-info/top_level.txt
lfkbenchmark-1.0.0b4.dist-info/WHEEL
lfkbenchmark-1.0.0b4.dist-info/RECORD
lfkbenchmark.libs/liblfk-benchmark-ea264d30.so
