Metadata-Version: 2.1
Name: lfkbenchmark
Version: 1.0.0b4
Summary: Python Interface to lfk-mp-benchmark
Author: quanon
Author-email: akshay@kivy.org
License-File: LICENSE
